pycalphad/variables.py
pycalphad/__init__.py
pycalphad/model.py
pycalphad/mapping/compat_api.py
pycalphad/mapping/primitives.py
pycalphad/mapping/plotting.py
pycalphad/mapping/zpf_equilibrium.py
pycalphad/mapping/__init__.py
pycalphad/mapping/starting_points.py
pycalphad/mapping/utils.py
pycalphad/mapping/zpf_checks.py
pycalphad/mapping/strategy/step_strategy.py
pycalphad/mapping/strategy/strategy_data.py
pycalphad/mapping/strategy/strategy_base.py
pycalphad/mapping/strategy/binary_strategy.py
pycalphad/mapping/strategy/__init__.py
pycalphad/mapping/strategy/isopleth_strategy.py
pycalphad/mapping/strategy/ternary_strategy.py
pycalphad/core/equilibrium.py
pycalphad/core/solver.py
pycalphad/core/lower_convex_hull.py
pycalphad/core/minimizer.pxd
pycalphad/core/calculate.py
pycalphad/core/starting_point.py
pycalphad/core/composition_set.pxd
pycalphad/core/phase_rec.cpython-311-darwin.so
pycalphad/core/constants.py
pycalphad/core/cache.py
pycalphad/core/__init__.py
pycalphad/core/polytope.py
pycalphad/core/minimizer.cpython-311-darwin.so
pycalphad/core/light_dataset.py
pycalphad/core/conditions.py
pycalphad/core/composition_set.cpython-311-darwin.so
pycalphad/core/halton.py
pycalphad/core/utils.py
pycalphad/core/hyperplane.pxd
pycalphad/core/phase_rec.pxd
pycalphad/core/hyperplane.cpython-311-darwin.so
pycalphad/core/constraints.py
pycalphad/core/errors.py
pycalphad/core/workspace.py
pycalphad/core/eqsolver.cpython-311-darwin.so
pycalphad/plot/__init__.py
pycalphad/plot/triangular.py
pycalphad/plot/ternary.py
pycalphad/plot/utils.py
pycalphad/plot/eqplot.py
pycalphad/plot/binary/plot.py
pycalphad/plot/binary/__init__.py
pycalphad/plot/binary/map.py
pycalphad/plot/binary/zpf_boundary_sets.py
pycalphad/plot/binary/compsets.py
pycalphad/io/tdb_keywords.py
pycalphad/io/database.py
pycalphad/io/__init__.py
pycalphad/io/grammar.py
pycalphad/io/tdb.py
pycalphad/io/cs_dat.py
pycalphad/tests/test_energy.py
pycalphad-0.11.1.dist-info/RECORD
pycalphad-0.11.1.dist-info/WHEEL
pycalphad-0.11.1.dist-info/top_level.txt
pycalphad-0.11.1.dist-info/METADATA
pycalphad-0.11.1.dist-info/licenses/LICENSE.txt
