Metadata-Version: 2.4
Name: pycalphad
Version: 0.11.1
Summary: CALPHAD tools for designing thermodynamic models, calculating phase diagrams and investigating phase equilibria.
Home-page: https://pycalphad.org/
Author: Richard Otis
Author-email: richard.otis@outlook.com
License: MIT
Classifier: Development Status :: 4 - Beta
Classifier: Intended Audience :: Science/Research
Classifier: Topic :: Scientific/Engineering :: Physics
Classifier: Topic :: Scientific/Engineering :: Chemistry
Classifier: License :: OSI Approved :: MIT License
Classifier: Programming Language :: Python :: 3
Classifier: Programming Language :: Python :: 3.11
Classifier: Programming Language :: Python :: 3.12
Classifier: Programming Language :: Python :: 3.13
License-File: LICENSE.txt
Requires-Dist: matplotlib>=3.3
Requires-Dist: numpy>=1.13
Requires-Dist: pint
Requires-Dist: pyparsing>=2.4
Requires-Dist: pytest
Requires-Dist: pytest-cov
Requires-Dist: runtype
Requires-Dist: scipy
Requires-Dist: setuptools_scm[toml]>=6.0
Requires-Dist: symengine<0.14,>=0.9.2
Requires-Dist: tinydb>=3.8
Requires-Dist: typing_extensions
Requires-Dist: xarray>=0.11.2
Dynamic: author
Dynamic: author-email
Dynamic: classifier
Dynamic: description
Dynamic: description-content-type
Dynamic: home-page
Dynamic: license
Dynamic: license-file
Dynamic: requires-dist
Dynamic: summary
